main.py
memorymap-0.0.0.dist-info/METADATA
memorymap-0.0.0.dist-info/WHEEL
memorymap-0.0.0.dist-info/top_level.txt
memorymap-0.0.0.dist-info/RECORD
