Metadata-Version: 2.4
Name: memorymap
Version: 0.0.0
Summary: a map-like data structure backed by Redis (compatible servers)
Requires-Python: >=3.13
